scv/__init__.py
scv/cli.py
scv/utils.py
scv-2.0.0.dist-info/LICENSE
scv-2.0.0.dist-info/METADATA
scv-2.0.0.dist-info/WHEEL
scv-2.0.0.dist-info/entry_points.txt
scv-2.0.0.dist-info/top_level.txt
scv-2.0.0.dist-info/RECORD
