Metadata-Version: 2.1
Name: scv
Version: 2.0.0
Summary: better package manager - python package manager
Home-page: https://github.com/SmilingXinyi/scv
Author: blaite
Author-email: smilingxinyi@gmail.com
License: MIT
Keywords: package-manager requirements
Platform: UNKNOWN
Requires-Dist: enum34
Requires-Dist: pyyaml
Requires-Dist: virtualenv
